MANIFEST.in
requirements.txt
setup.py
powser.egg-info/PKG-INFO
powser.egg-info/SOURCES.txt
powser.egg-info/dependency_links.txt
powser.egg-info/entry_points.txt
powser.egg-info/not-zip-safe
powser.egg-info/requires.txt
powser.egg-info/top_level.txt
src/__init__.py
src/cdnjs.py
src/install.py
src/main.py
src/search.py
src/show.py
src/version.py