Metadata-Version: 1.0
Name: powser
Version: 1.0.2
Summary: Front-end package manager inspired by bower utilizing cdnjs. See https://github.com/JDeuce/powser for more.
Home-page: https://github.com/JDeuce/powser
Author: Josh Jaques
Author-email: jjaques@gmail.com
License: MIT License
Keywords: front-end package management cdnjs bower
Platform: UNKNOWN
